{"stats":{"minecraft:picked_up":{"minecraft:dirt":3},"minecraft:dropped":{"minecraft:dirt":3},"minecraft:mined":{"minecraft:dirt":1},"minecraft:custom":{"minecraft:sprint_one_cm":644,"minecraft:time_since_rest":713,"minecraft:walk_one_cm":1714,"minecraft:total_world_time":1622,"minecraft:leave_game":1,"minecraft:fly_one_cm":1130,"minecraft:crouch_one_cm":49,"minecraft:sneak_time":12,"minecraft:play_time":713,"minecraft:jump":9,"minecraft:time_since_death":713,"minecraft:drop":3},"minecraft:used":{"minecraft:command_block":1,"minecraft:dirt":1}},"DataVersion":4440}